[
  {"traceId": "17dc8c8a2c5f3ad5", "name": "/sleep", "id": "b73350fb01c09f2d", "parentId": "b007995ba1ff131e", "serviceName": "docker-debug", "hostIPv4": "10.1.3.71", "binaryAnnotations": [{"key": "component", "value": "flask"}, {"key": "sleep", "value": 5}], "timestamp": 1577468382812652},
  {"traceId": "17dc8c8a2c5f3ad5", "name": "docker-debug.sleep", "id": "b007995ba1ff131e", "parentId": "7800b113b233ee63", "serviceName": "docker-debug", "hostIPv4": "10.1.3.71", "binaryAnnotations": [{"key": "component", "value": "Flask"}, {"key": "http.method", "value": "GET"}, {"key": "http.url", "value": "http://127.0.0.1:5000/sleep/5"}, {"key": "span.kind", "value": "server"}], "timestamp": 1577468382812669},
  {"traceId": "17dc8c8a2c5f3ad5", "name": "/sleep/5", "id": "d9fecab3a39f9a73", "serviceName": "nginx-ingress", "binaryAnnotations": [{"key": "component", "value": "nginx"}, {"key": "http.host", "value": "localhost:8080"}, {"key": "http.method", "value": "GET"}, {"key": "http.status_code", "value": "200"}, {"key": "http.status_line", "value": "200 OK"}, {"key": "http.url", "value": "http://localhost:8080/sleep/5"}, {"key": "http_user_agent", "value": "Mozilla/5.0 (Macintosh; Intel Mac OS X 10.14; rv:71.0) Gecko/20100101 Firefox/71.0"}, {"key": "lc", "value": "nginx-ingress"}, {"key": "nginx.worker_pid", "value": 7}, {"key": "peer.address", "value": "127.0.0.1:58868"}, {"key": "request_id", "value": "aaa0fb401020734fc6fd22dbd33abc96"}, {"key": "upstream.address", "value": "10.105.217.58:80"}, {"key": "version", "value": 0.92}], "timestamp": 1577468375926000, "duration": 5013407},
  {"traceId": "17dc8c8a2c5f3ad5", "name": "/sleep/5", "id": "7800b113b233ee63", "parentId": "d9fecab3a39f9a73", "serviceName": "docker-debug", "binaryAnnotations": [{"key": "component", "value": "nginx"}, {"key": "http.host", "value": "docker-debug.opa-tracing.svc.cluster.local"}, {"key": "http.method", "value": "GET"}, {"key": "http.status_code", "value": "200"}, {"key": "http.status_line", "value": "200 OK"}, {"key": "http.url", "value": "http://docker-debug.opa-tracing.svc.cluster.local/sleep/5"}, {"key": "http_user_agent", "value": "Mozilla/5.0 (Macintosh; Intel Mac OS X 10.14; rv:71.0) Gecko/20100101 Firefox/71.0"}, {"key": "lc", "value": "docker-debug"}, {"key": "nginx.worker_pid", "value": 7}, {"key": "peer.address", "value": "10.1.3.57:45518"}, {"key": "request_id", "value": "f4c81620a0468a02c808833902fb85ff"}, {"key": "upstream.address", "value": "127.0.0.1:5000"}, {"key": "version", "value": ""}], "timestamp": 1577468375929000, "duration": 5018656}
]
